{"Oq06LyWibdeQPcHxeUzuAw==":"mbr-1920x1280.jpg","/3ro58mvm6b+nymOGpgNkQ==":"mbr-1920x1281.jpg","1GAEunjipJZou8E2Dwch+A==":"mbr-1-1920x1280.jpg","HNg6smXvbaqLVFxKDWm1Ng==":"mbr-2-1920x1280.jpg","7DTi/dYuJIN4JAAxHTGqSA==":"r100%20logo-122x33.png","/RvxzvauICAfsuJMBfPW8Q==":"logo-354x111.jpg","/5TxP6rB5Xsj6wML99MSww==":"logo2.png","UAc7kepzJPkrSn4uqTRvmw==":"background4.jpg","L6WzE7YJHwWbCvRxPxOmYA==":"r100%20logo-122x33.png","nGI9AGLY77JBqtz11G97dw==":"r100%20logo-122x33.png","RsUXRL8uu/BfD5D8hr+aHg==":"nothing-154x120.jpg","SOVO8Tlq3EX3F5OLNSyDZA==":"rt%20selection%203%20(1)-757x860.png","SWdFR5lrDPhABbJpDTchBw==":"rt%20selection%203%20(1)-757x860.png","xh8XiouIp3q58cjSPDKqvQ==":"rt%20selection%203%20(1)-757x860.png","UiSVPoHnNee8fZsxmpovNA==":"rt%20selection%201-1152x768.png","ZKtnAL7VeLIzA1EJkT+GaQ==":"rt%20selection%201-1152x768.png","x7+KYxhq9Od6ssOrTEpgoA==":"rt%20selection%201-1152x768.png","cnusJckEmUpvoJlCKeEupQ==":"rt%20selection%2016-1152x768.png","LdFCw+Q1ROudz7kQhrTkcw==":"rt%20selection%208-1152x768.png","gsR1SNb/3eVtuOm8lkjIyg==":"london-aerial-thames-guide.webp","63ogoBN33f3ENVQllockNA==":"rt%20selection%201-1152x768.png","q0Gpwz0zGw1D/pg6MT/asQ==":"background8.jpg","xt/cpb/8ZS1ebYrrLFdkIA==":"rt%20selection%203%20(1)-757x860.png","ZYXVHKB2+Y5efL1s+2synw==":"rt%20selection%203%20cropped-555x575.jpg","VWRmizUg3JzEXZkhNOhJbg==":"rt%20selection%208-1152x768.png","v6AwXMOkQVKYMghOhj6bMg==":"rt%20selection%205-768x1152.png","f6qE6tJHxTamLzsq+QWqcw==":"rt%20selection%205-768x1152.png","rdPtBiSikCoa0t13drpgxw==":"rt%20selection%205%20cropped-675x775.png","oE3r9EBUnSpJbkOFeVn8og==":"rt%20selection%205%20cropped-675x775.png","2PJCUWyAWUrv8NlyGH0PhQ==":"19roundtable-combo-superjumbo-2000x1334.jpg","dPVTnW4Ts7Up5lVOiJyevw==":"19roundtable-combo-superjumbo-2000x1334.jpeg","ppdyvbC7MU8VZgBXISumWA==":"19roundtable-combo-superjumbo-1-2000x1334.jpeg","JOLv0+eXu1TRgNFKpST2jQ==":"19roundtable-combo-superjumbo%202-2000x1638.png","W0npvsk2w5/KpFPm5g5NpQ==":"19roundtable-combo-superjumbo%202-2000x1638.png","0Cc+kQ2wP5XoET981hgT/w==":"woman-in-sme-bakery-xlarge.webp","bCk02Qn9Uz+M/u2Kb9bTdw==":"25426-14x3dyl-668x523.jpg","GsOeC0GF4s1oWo6pc3nt3Q==":"4000-1760x1170.jpg","+nBaaICNEdfaLlVB6EGthA==":"4000-1760x1170.jpeg","SpzPhURVClapnTotgZ+h8g==":"3500-1240x744.jpg","hovEHcM1it3tuy6MMmFJIg==":"3500-1240x744.jpeg","WWtXShHVra218uPUWP6EOw==":"19roundtable-2000x1638.jpeg","hXuqqtXDHkdlz72H0Z0kxg==":"19roundtable-1-2000x1638.jpeg","7KWV/AsZ6yiBozKiYR5AJA==":"19roundtable-2-2000x1638.jpeg","rpGMCx6VmuX3LMtT7RP2wg==":"19roundtable2-1786x1352.jpg","J/OMEHLhIKs6e0wA1a+Q8w==":"19roundtable2-1786x1352.jpeg","a/BaFKiwSB7CC406EGig4g==":"background6.jpg","Qpsei/9gl1+m3x/CoQ5S0Q==":"mbr-3-1920x1280.jpg","sci1uPs4GZT0AgB8VJnaIQ==":"6553-1760x1174.jpg","47zbuVVmUQHllWZ3pQLpaw==":"logo-354x111.jpeg","gZLcMaqIuMxAxACDFjfU6A==":"logo-resized-426x70.jpeg","x6ha2bHw4cz5opjjPxOJSw==":"logo-resized-1-426x70.jpeg","9cOezehrJ4mpVAZrw8IivA==":"logo-resized2-676x111.jpg","5PiUoh5aByWImovLpoHwzQ==":"logo-resized2-676x111.jpeg","37iyLYInkd9p/j91SC4Q1A==":"rt%20selection%2016-1152x768.png","YHhQz77q7iOzEyDEbK4N6A==":"background1.jpeg","u0fX0KL0MYpN5tHt1fjNJw==":"background1-1.jpeg","bWLZNOsATeO7Qd2Ck8CaJA==":"background1-2.jpeg","atVkVj1E1nyc1RcnBYB+mg==":"corps-676x344.png","7T9fA/6vtF9nNK1O26aacQ==":"smes-676x343.png","/IsEH8vh+J9/6Sf93q+FPA==":"ngos-676x343.png","4O8Etg0nLE3eWpiFzDttiA==":"shutterstock-592190993-1000x667.jpg","NPqdorY4wxq7DcnDnMEP9g==":"how-to-determine-your-salary-business-owner-1000x667.jpg","h1rBSrBLnXWQT6wdmEUf5w==":"logo-resized3-746x92.jpg","pa5Dkwo/T1qgW/t0h+fQvA==":"background5.jpg","mIIbxW0r7dEZSbMPwcoYdg==":"background2.jpg","Jcs6obEA4ZzcVA2V02K2sg==":"mbr-1920x1080.jpg","FLVGID2HYhUbM0B25kFtug==":"mbr-4-1920x1280.jpg","dXY1NqH+MUkErWugNY57xw==":"mbr-4-1920x1280.jpeg","TP+xr9A5aFDBEz71v8+o8A==":"mbr-1-1920x1281.jpg","Dckbyeo6PcqSIArYAPwQcQ==":"mbr-1-1920x1281.jpeg","SemKRc30V+zTm+++a3cNLg==":"mbr-1920x1706.jpg","Fb3mipdLTYGP9yOlh4TlmA==":"3500-1-1240x744.jpeg","yo6ZPqd7476Lcb+mB2C1ZQ==":"rt%20selection%205%20cropped-675x775.png","IRuzWbs8H7v3opBe258XDQ==":"london-aerial-thames-guide-1.webp","hGar6m94APCFsl7BIxEqYw==":"rt%20selection%208-1152x768.png","sT80Y4RCGNBrSInGgrjIuA==":"background3.jpg","OM6hTwqMAQpTVhLcPG86xg==":"background1.jpg","z6ZfLgd9OBzf8K4H4ABlWw==":"background7.jpg","vXeDnry8kFM1hkjPPoS7OA==":"london-aerial-thames-guide-2.webp","qOgVNNOlm9Rt1MVJrnbkJg==":"mbr-1920x1706.jpeg","wkq1EwN0zFrL8ATGeY5k3w==":"array%20#1-834x188.jpg","Jbfi/+OAhDbOCMEVOQBmHg==":"cnpb7gzg-834x469.jpg","288juLiUKSo0VsPjbMR/ng==":"array1-834x188.png","xoGOMFdSIW15ypkdoUeSbg==":"array1-1-834x188.png","M6PT9Hy3Y5pdMX8xaRpLtA==":"array1-2000x450.png","0tv7q/UjzKhjULxf6tE1dg==":"array1-1-2000x450.png","O5keWITYqlhSXgVwwpdnxA==":"array2-1382x311.jpeg","pNPjwcNGhWdKv0YajRZw0g==":"array3-1382x311.jpg","/TMU0sadcatuXXEVWIy6rw==":"array4-1382x311.jpg","iHRBbXQQCU8r+nrg3zh+pA==":"array5-1382x311.jpg","DXInQTII6oz3vj3mKXYW1Q==":"array5-1-1382x311.jpg","xu1Ooo0ggnfyCibr7CTxIA==":"report%20on%20progress-676x319.jpg","il6xYrnsRi4hox2F0Fr4TQ==":"seek%20help%20to%20progress-676x319.jpg","v2HcBG7YAzrqLyriu8XCWw==":"array2-1382x311.jpg","NsDzulwcG2m9tmI2Eyjcmg==":"array3-1382x318.jpg","lIsIVqQGmFRFinYAyUbxSg==":"array4-1382x318.jpg","gmWC5RYThs9Q6QDJeHzFHQ==":"array5-1382x318.jpg","pgxR4u3gjawKVLSeAYT9Jw==":"next%20issue-676x319.jpg","ZKHhQGseHVFdEUn+qhw41g==":"xr%20drum-554x369.png","Jnvc6tjylFxzCqLi6mOPDw==":"xr%20bau-554x369.png","JQg94/iKflG9YUNPLrmw9A==":"skynews-barclays-climate-change-4957918-554x312.jpg","K6x+8j18zi63veudtizQKA==":"142960-cant-breathe-protests-520x292.jpg","TQw35DB5RD7jjTU0SuHlZg==":"skynews-barclays-climate-change-4957918-554x312.jpeg","L3vNEfacOE6pTCdtkjZkjw==":"xr%20drum-554x369.png","NmeEeoZhDXxKMCEFSxQyOw==":"xr%20bau-554x369.png","5oJd6qWtJ/1RDBJs1LsjPw==":"sme%20image3-474x266.jpg","w1R0NzT8gvTHmMurA28Zxg==":"sme%20image%202-474x316.jpg","Xe3ADncxebJJhliaJBZqsw==":"sme%20image-474x316.jpg","UGBuNdAEQ7PzZ0mlAuTWRw==":"sme%20image4-474x145.jpg","179uQMAAgyoeZQI5NiFn0A==":"sme%20image4-474x145.jpeg","WCPhrU6DVbvmBs+MUV2MYw==":"sme%20image%202-474x316.jpeg","31NoNa2OWOgnLzFyB7g3bw==":"sme%20image5.webp","0yrTw6wK3opRGYDqc+jLyQ==":"sme%20image5.webp","Z7AHQS/joQK9v6op6wLHCw==":"sme%20image6-474x316.jpg","GGGIvHout+yGjOzNQE6i4w==":"sme%20image6-474x316.jpeg","iBl/g3AINjGFs7AVj4FrCg==":"corp%20image4-474x316.jpg","6LTbud5COUpuMozRjOHT4g==":"corp%20image3-474x316.jpg","3g1Au6U9WwoS9JnQ8hxofA==":"corp%20image2-300x168.jpg","2eFjt2bPaM3Dpr2hdRj+8w==":"corp%20image-284x177.jpg","DHuXjejta0fkQTcVP2fFMQ==":"corp%20image5-474x356.jpg","hg6fyNP+l/Ais6BTyuzk7Q==":"corp%20image5-474x356.jpeg","2Rpxss1Aig5vdoVQWl9wpQ==":"corp%20image-284x177.jpeg","p5rrwdp5d9NNEGe/vYgxmA==":"corp%20image4-474x316.jpeg","KxfjGACb8wHBdyupxAA2dw==":"corp%20image3-474x316.jpeg","hZFuTRtkZAZgstTVMzZROQ==":"corp%20image6-474x335.jpeg","+bOflpFcZvDXOU/5vkM8UQ==":"corp%20image7-474x316.jpeg","5E5HsEiqY344WZmLJOSCpQ==":"corp%20image8-554x366.jpg","jVhrmGkImZTGrgumNeQi1w==":"corp%20image8-554x366.jpeg","lvvnJr2SO7AxEPmHbfpgig==":"polar%20bear-554x420.jpg","gEC7XEIC5L5HhfrM3ZI7+w==":"polar%20bear-554x420.jpeg","z8nw/dePcXnku0As52UaoQ==":"logo-resized5-986x655.jpg","YIzKzVZZudYnDq0jiUUiKw==":"logo-resized6-182x93.jpg","KcE4aucif8gaZzbSZpaKlQ==":"logo-resized6-182x93.jpeg","vfJcF2PhCSjU5jnaOOcLMA==":"logo-resized7-262x151.jpg","3cRn8P3IRH3hRCG2WA5+qQ==":"logo-resized7-262x151.jpeg","ZI2rhBtXacJMlMkXg+RkeA==":"logo-resized8-454x166.jpg"}